README.md
setup.py
mysqldb_rich/__init__.py
mysqldb_rich/_advance.py
mysqldb_rich/_conf_db.py
mysqldb_rich/_db.py
mysqldb_rich/_execute.py
mysqldb_rich/_table.py
mysqldb_rich.egg-info/PKG-INFO
mysqldb_rich.egg-info/SOURCES.txt
mysqldb_rich.egg-info/dependency_links.txt
mysqldb_rich.egg-info/requires.txt
mysqldb_rich.egg-info/top_level.txt
mysqldb_rich/db2/__init__.py
mysqldb_rich/db2/_advance.py
mysqldb_rich/db2/_conf_db.py
mysqldb_rich/db2/_db.py
mysqldb_rich/db2/_execute.py
mysqldb_rich/db2/_table.py
mysqldb_rich/db2/__init__.py
mysqldb_rich/db2/_advance.py
mysqldb_rich/db2/_conf_db.py
mysqldb_rich/db2/_db.py
mysqldb_rich/db2/_execute.py
mysqldb_rich/db2/_table.py