Metadata-Version: 1.0
Name: mysqldb-rich
Version: 4.2.6
Summary: rich mysqldb
Home-page: https://github.com/meisanggou/mysqldb-rich
Author: meisanggou
Author-email: zhouheng@gene.ac
License: MIT
Keywords: mysqldb-rich
Platform: UNKNOWN
